pyuuid_util/__init__.py
pyuuid_util/uuid_util.py
pyuuid_util-1.0.0.dist-info/LICENSE
pyuuid_util-1.0.0.dist-info/METADATA
pyuuid_util-1.0.0.dist-info/WHEEL
pyuuid_util-1.0.0.dist-info/top_level.txt
pyuuid_util-1.0.0.dist-info/zip-safe
pyuuid_util-1.0.0.dist-info/RECORD
